yahooauction_bidder-0.0.8.dist-info/METADATA
yahooauction_bidder-0.0.8.dist-info/RECORD
yahooauction_bidder-0.0.8.dist-info/WHEEL
yahooauction_bidder-0.0.8.dist-info/top_level.txt
yahooauctionbidder/__init__.py
yahooauctionbidder/bid.py
yahooauctionbidder/logger.py
yahooauctionbidder/login.py
