Metadata-Version: 2.1
Name: yahooauction-bidder
Version: 0.0.8
Summary: programmable bidding system by wrapping selenium & chrome
Home-page: https://github.com/umihico/yahooauction-bidder
Author: umihico
Author-email: umihico@users.noreply.github.com
License: MIT
Platform: UNKNOWN
Classifier: Programming Language :: Python :: 3.6
